diffpy/__init__.py
diffpy/morph/__init__.py
diffpy/morph/log.py
diffpy/morph/morph_api.py
diffpy/morph/morph_io.py
diffpy/morph/morphapp.py
diffpy/morph/morphpy.py
diffpy/morph/plot.py
diffpy/morph/refine.py
diffpy/morph/tools.py
diffpy/morph/version.py
diffpy/morph/morph_helpers/__init__.py
diffpy/morph/morph_helpers/transformpdftordf.py
diffpy/morph/morph_helpers/transformrdftopdf.py
diffpy/morph/morphs/__init__.py
diffpy/morph/morphs/morph.py
diffpy/morph/morphs/morphchain.py
diffpy/morph/morphs/morphfuncx.py
diffpy/morph/morphs/morphfuncxy.py
diffpy/morph/morphs/morphfuncy.py
diffpy/morph/morphs/morphishape.py
diffpy/morph/morphs/morphresolution.py
diffpy/morph/morphs/morphrgrid.py
diffpy/morph/morphs/morphscale.py
diffpy/morph/morphs/morphshape.py
diffpy/morph/morphs/morphshift.py
diffpy/morph/morphs/morphsmear.py
diffpy/morph/morphs/morphsqueeze.py
diffpy/morph/morphs/morphstretch.py
diffpy_morph-0.3.1.dist-info/licenses/AUTHORS.rst
diffpy_morph-0.3.1.dist-info/licenses/LICENSE.rst
diffpy_morph-0.3.1.dist-info/METADATA
diffpy_morph-0.3.1.dist-info/WHEEL
diffpy_morph-0.3.1.dist-info/entry_points.txt
diffpy_morph-0.3.1.dist-info/top_level.txt
diffpy_morph-0.3.1.dist-info/RECORD
